CHANGELOG
COPYING
COPYING.LESSER
MANIFEST.in
README
setup.py
cfg/wigxjpf_config.h
example/ccsimple.cc
example/ccsimple.good
example/cfail.c
example/cfail.expect
example/csimple.c
example/csimple.good
example/cthreadedsimple.c
example/cthreadedsimple.good
example/evaltable.huge.good
example/evaltable.large.good
example/evaltable.sh
example/evaltable.small.good
example/fsimple.f
example/fsimple.good
example/py_numba.py
example/pyfail.expect
example/pyfail.py
example/pysimple.good
example/pysimple.py
example/wigxjpf.c
inc/fpsimplexj.h
inc/wigxjpf.h
inc/wigxjpf_quadmath.h
pywigxjpf/__init__.py
pywigxjpf/pywigxjpf.py
pywigxjpf/pywigxjpf_ffi_builder.py
pywigxjpf.egg-info/PKG-INFO
pywigxjpf.egg-info/SOURCES.txt
pywigxjpf.egg-info/dependency_links.txt
pywigxjpf.egg-info/requires.txt
pywigxjpf.egg-info/top_level.txt
pywigxjpf/pregen/wigxjpf_auto_config.h
src/c_wrap.c
src/c_wrap.h
src/c_wrap_float128.c
src/calc.c
src/calc.h
src/calc_dbl.h
src/calc_float128.c
src/calc_minmax.h
src/fortran_wrap.c
src/fpsimple.c
src/fpsimple_log.c
src/fpsimple_precalc.c
src/fwigxjpf.f
src/multi_word_int.h
src/multi_word_int_dbl.h
src/multi_word_int_float128.h
src/prime_factor.c
src/prime_factor.h
src/test_cc_dbl.c
src/trivial_zero.c
src/wigxjpf_error.c
src/wigxjpf_error.h