Metadata-Version: 2.1
Name: pywigxjpf
Version: 1.11
Summary: Wigner Symbols
Home-page: http://fy.chalmers.se/subatom/wigxjpf
Author: C. Forssen and H. T. Johansson
License: GPLv3
Platform: UNKNOWN
